univalidator/__init__.py
univalidator/py.typed
univalidator/abstractions/__init__.py
univalidator/abstractions/_base_composite_validator.py
univalidator/abstractions/_base_validator.py
univalidator/composites/__init__.py
univalidator/composites/_composite_validator.py
univalidator/validators/__init__.py
univalidator/validators/_mx_email_record_validator.py
univalidator/validators/_regex_email_validator.py
univalidator/validators/_regex_validator.py
univalidator-0.2.1.dist-info/METADATA
univalidator-0.2.1.dist-info/WHEEL
univalidator-0.2.1.dist-info/entry_points.txt
univalidator-0.2.1.dist-info/licenses/LICENSE
univalidator-0.2.1.dist-info/RECORD
