Metadata-Version: 2.4
Name: univalidator
Version: 0.2.1
Summary: A lightweight, type-safe email validator with support of multiple validator.
Project-URL: Homepage, https://github.com/shaileshpandit141/univalidator
Project-URL: Repository, https://github.com/shaileshpandit141/univalidator
Project-URL: Issues, https://github.com/shaileshpandit141/univalidator/issues
Author-email: shaileshpandit141 <shaileshpandit141@gmail.com>
License: # MIT License
License-File: LICENSE
Keywords: composite-validator,data-validation,dns,email,email-validator,mx-record,python-validator,regex,type-safe-validation,typed-validator,validation,validator
Classifier: Development Status :: 4 - Beta
Classifier: Intended Audience :: Developers
Classifier: License :: OSI Approved :: MIT License
Classifier: Programming Language :: Python :: 3
Classifier: Programming Language :: Python :: 3.11
Classifier: Programming Language :: Python :: 3.12
Classifier: Programming Language :: Python :: 3.13
Classifier: Topic :: Internet :: Name Service (DNS)
Classifier: Topic :: Software Development :: Libraries
Classifier: Topic :: Software Development :: Libraries :: Python Modules
Classifier: Topic :: Utilities
Classifier: Typing :: Typed
Requires-Python: >=3.13
Requires-Dist: dnspython>=2.7.0
Provides-Extra: dev
Requires-Dist: mypy; extra == 'dev'
Requires-Dist: pytest; extra == 'dev'
Requires-Dist: ruff; extra == 'dev'
